{
    "sourceFile": "resources/views/features/submission/Approve.blade.php",
    "activeCommit": 0,
    "commits": [
        {
            "activePatchIndex": 22,
            "patches": [
                {
                    "date": 1666747747936,
                    "content": "Index: \n===================================================================\n--- \n+++ \n"
                },
                {
                    "date": 1666749284687,
                    "content": "Index: \n===================================================================\n--- \n+++ \n@@ -13,14 +13,9 @@\n                         <div class=\"form-group\">\n                             <div class=\"row\">\n                                 <div class=\"col-md-6 col-sm-12\">\n                                     <label>Form City</label>\n-                                    <select class=\"js-example w-100\" name=\"form_city_id\">\n-                                        <option selected hidden>Select City</option>\n-                                        @foreach ($city as $item)\n-                                            <option value=\"{{ $item->id }}\">{{ $item->city }}</option>\n-                                        @endforeach\n-                                    </select>\n+                                    in\n                                 </div>\n                                 <div class=\"col-md-6 col-sm-12\">\n                                     <label>To City</label>\n                                     <select class=\"js-example-basic w-100\" name=\"to_city_id\">\n"
                },
                {
                    "date": 1666749295516,
                    "content": "Index: \n===================================================================\n--- \n+++ \n@@ -13,9 +13,9 @@\n                         <div class=\"form-group\">\n                             <div class=\"row\">\n                                 <div class=\"col-md-6 col-sm-12\">\n                                     <label>Form City</label>\n-                                    in\n+                                    <input type=\"text\" class=\"form-control\">\n                                 </div>\n                                 <div class=\"col-md-6 col-sm-12\">\n                                     <label>To City</label>\n                                     <select class=\"js-example-basic w-100\" name=\"to_city_id\">\n"
                },
                {
                    "date": 1666749301294,
                    "content": "Index: \n===================================================================\n--- \n+++ \n@@ -13,9 +13,9 @@\n                         <div class=\"form-group\">\n                             <div class=\"row\">\n                                 <div class=\"col-md-6 col-sm-12\">\n                                     <label>Form City</label>\n-                                    <input type=\"text\" class=\"form-control\">\n+                                    <input type=\"text\" class=\"form-control\" value=\"\">\n                                 </div>\n                                 <div class=\"col-md-6 col-sm-12\">\n                                     <label>To City</label>\n                                     <select class=\"js-example-basic w-100\" name=\"to_city_id\">\n"
                },
                {
                    "date": 1666749309839,
                    "content": "Index: \n===================================================================\n--- \n+++ \n@@ -11,8 +11,9 @@\n                         @csrf\n                         @method('POST')\n                         <div class=\"form-group\">\n                             <div class=\"row\">\n+                                <input type=\"id\" value=\"\">\n                                 <div class=\"col-md-6 col-sm-12\">\n                                     <label>Form City</label>\n                                     <input type=\"text\" class=\"form-control\" value=\"\">\n                                 </div>\n"
                },
                {
                    "date": 1666750209811,
                    "content": "Index: \n===================================================================\n--- \n+++ \n@@ -14,9 +14,9 @@\n                             <div class=\"row\">\n                                 <input type=\"id\" value=\"\">\n                                 <div class=\"col-md-6 col-sm-12\">\n                                     <label>Form City</label>\n-                                    <input type=\"text\" class=\"form-control\" value=\"\">\n+                                    <input type=\"text\" class=\"form-control\" value=\"\" readonly>\n                                 </div>\n                                 <div class=\"col-md-6 col-sm-12\">\n                                     <label>To City</label>\n                                     <select class=\"js-example-basic w-100\" name=\"to_city_id\">\n"
                },
                {
                    "date": 1666750225858,
                    "content": "Index: \n===================================================================\n--- \n+++ \n@@ -11,9 +11,9 @@\n                         @csrf\n                         @method('POST')\n                         <div class=\"form-group\">\n                             <div class=\"row\">\n-                                <input type=\"id\" value=\"\">\n+                                <input type=d\" value=\"\">\n                                 <div class=\"col-md-6 col-sm-12\">\n                                     <label>Form City</label>\n                                     <input type=\"text\" class=\"form-control\" value=\"\" readonly>\n                                 </div>\n"
                },
                {
                    "date": 1666750230968,
                    "content": "Index: \n===================================================================\n--- \n+++ \n@@ -11,9 +11,9 @@\n                         @csrf\n                         @method('POST')\n                         <div class=\"form-group\">\n                             <div class=\"row\">\n-                                <input type=d\" value=\"\">\n+                                <input type=\"hidden\" value=\"\">\n                                 <div class=\"col-md-6 col-sm-12\">\n                                     <label>Form City</label>\n                                     <input type=\"text\" class=\"form-control\" value=\"\" readonly>\n                                 </div>\n"
                },
                {
                    "date": 1666750243152,
                    "content": "Index: \n===================================================================\n--- \n+++ \n@@ -17,15 +17,10 @@\n                                     <label>Form City</label>\n                                     <input type=\"text\" class=\"form-control\" value=\"\" readonly>\n                                 </div>\n                                 <div class=\"col-md-6 col-sm-12\">\n-                                    <label>To City</label>\n-                                    <select class=\"js-example-basic w-100\" name=\"to_city_id\">\n-                                        <option selected hidden>Select City</option>\n-                                        @foreach ($city as $item)\n-                                            <option value=\"{{ $item->id }}\">{{ $item->city }}</option>\n-                                        @endforeach\n-                                    </select>\n+                                    <label>Form City</label>\n+                                    <input type=\"text\" class=\"form-control\" value=\"\" readonly>\n                                 </div>\n \n                             </div>\n                         </div>\n"
                },
                {
                    "date": 1666750251907,
                    "content": "Index: \n===================================================================\n--- \n+++ \n@@ -17,12 +17,11 @@\n                                     <label>Form City</label>\n                                     <input type=\"text\" class=\"form-control\" value=\"\" readonly>\n                                 </div>\n                                 <div class=\"col-md-6 col-sm-12\">\n-                                    <label>Form City</label>\n+                                    <label>To City</label>\n                                     <input type=\"text\" class=\"form-control\" value=\"\" readonly>\n                                 </div>\n-\n                             </div>\n                         </div>\n                         <div class=\"form-group\">\n                             <div class=\"row\">\n"
                },
                {
                    "date": 1666750266247,
                    "content": "Index: \n===================================================================\n--- \n+++ \n@@ -24,25 +24,16 @@\n                             </div>\n                         </div>\n                         <div class=\"form-group\">\n                             <div class=\"row\">\n+                                <input type=\"hidden\" value=\"\">\n                                 <div class=\"col-md-6 col-sm-12\">\n-                                    <label for=\"city\">Start Date</label>\n-                                    <input type=\"date\" class=\"form-control @error('city') is-invalid @enderror\"\n-                                        id=\"city\" autocomplete=\"off\" placeholder=\"Solo\" name=\"from\"\n-                                        autocomplete=\"off\" value=\"{{ old('city') }}\">\n-                                    @error('city')\n-                                        <div class=\"invalid-feedback\">{{ $message }}</div>\n-                                    @enderror\n+                                    <label>Form City</label>\n+                                    <input type=\"text\" class=\"form-control\" value=\"\" readonly>\n                                 </div>\n                                 <div class=\"col-md-6 col-sm-12\">\n-                                    <label for=\"to\">End Date</label>\n-                                    <input type=\"date\" class=\"form-control @error('city') is-invalid @enderror\"\n-                                        id=\"to\" autocomplete=\"off\" placeholder=\"Solo\" name=\"to\"\n-                                        autocomplete=\"off\" value=\"{{ old('city') }}\">\n-                                    @error('city')\n-                                        <div class=\"invalid-feedback\">{{ $message }}</div>\n-                                    @enderror\n+                                    <label>To City</label>\n+                                    <input type=\"text\" class=\"form-control\" value=\"\" readonly>\n                                 </div>\n                             </div>\n                         </div>\n                         <div class=\"form-group\">\n"
                },
                {
                    "date": 1666750272598,
                    "content": "Index: \n===================================================================\n--- \n+++ \n@@ -40,9 +40,9 @@\n                             <div class=\"row\">\n                                 <div class=\"col-lg-12\">\n                                     <label class=\"col-form-label\">Text Area</label>\n                                     <textarea id=\"description\" class=\"form-control\" maxlength=\"100\" rows=\"8\"\n-                                        placeholder=\"This textarea has a limit of 100 chars.\" name=\"desccription\"></textarea>\n+                                        placeholder=\"This textarea has a limit of 100 chars.\" name=\"desccription\" readonly></textarea>\n                                 </div>\n                             </div>\n                         </div>\n                         <div class=\"row\">\n"
                },
                {
                    "date": 1666750284261,
                    "content": "Index: \n===================================================================\n--- \n+++ \n@@ -26,9 +26,9 @@\n                         <div class=\"form-group\">\n                             <div class=\"row\">\n                                 <input type=\"hidden\" value=\"\">\n                                 <div class=\"col-md-6 col-sm-12\">\n-                                    <label>Form City</label>\n+                                    <label>Start Date</label>\n                                     <input type=\"text\" class=\"form-control\" value=\"\" readonly>\n                                 </div>\n                                 <div class=\"col-md-6 col-sm-12\">\n                                     <label>To City</label>\n"
                },
                {
                    "date": 1666750289691,
                    "content": "Index: \n===================================================================\n--- \n+++ \n@@ -30,9 +30,9 @@\n                                     <label>Start Date</label>\n                                     <input type=\"text\" class=\"form-control\" value=\"\" readonly>\n                                 </div>\n                                 <div class=\"col-md-6 col-sm-12\">\n-                                    <label>To City</label>\n+                                    <label>End Date</label>\n                                     <input type=\"text\" class=\"form-control\" value=\"\" readonly>\n                                 </div>\n                             </div>\n                         </div>\n"
                },
                {
                    "date": 1666750304951,
                    "content": "Index: \n===================================================================\n--- \n+++ \n@@ -45,14 +45,11 @@\n                                 </div>\n                             </div>\n                         </div>\n                         <div class=\"row\">\n-                            <div class=\"col-md-4\"></div>\n-                            <div class=\"col-md-4\">\n-                                <label for=\"\" class=\"form Label\">Total Perjalaan Dinas</label>\n-                                <h3>O Hari</h3>\n-                            </div>\n-                            <div class=\"col-md-4\"></div>\n+                             <div class=\"col-md-12\">\n+                                \n+                             </div>\n                         </div>\n                         <div class=\"mb-3\">\n                             <button type=\"submit\" class=\"btn btn-primary mr-2\">Submit</button>\n                             <button class=\"btn btn-light\">Cancel</button>\n"
                },
                {
                    "date": 1666750312302,
                    "content": "Index: \n===================================================================\n--- \n+++ \n@@ -45,11 +45,11 @@\n                                 </div>\n                             </div>\n                         </div>\n                         <div class=\"row\">\n-                             <div class=\"col-md-12\">\n-                                \n-                             </div>\n+                            <div class=\"col-12\">\n+\n+                            </div>\n                         </div>\n                         <div class=\"mb-3\">\n                             <button type=\"submit\" class=\"btn btn-primary mr-2\">Submit</button>\n                             <button class=\"btn btn-light\">Cancel</button>\n"
                },
                {
                    "date": 1666750321018,
                    "content": "Index: \n===================================================================\n--- \n+++ \n@@ -46,9 +46,11 @@\n                             </div>\n                         </div>\n                         <div class=\"row\">\n                             <div class=\"col-12\">\n+                                <table class=\"table\">\n \n+                                </table>\n                             </div>\n                         </div>\n                         <div class=\"mb-3\">\n                             <button type=\"submit\" class=\"btn btn-primary mr-2\">Submit</button>\n"
                },
                {
                    "date": 1666750327765,
                    "content": "Index: \n===================================================================\n--- \n+++ \n@@ -47,9 +47,13 @@\n                         </div>\n                         <div class=\"row\">\n                             <div class=\"col-12\">\n                                 <table class=\"table\">\n+                                    <thead>\n+                                        <tr>\n \n+                                        </tr>\n+                                    </thead>\n                                 </table>\n                             </div>\n                         </div>\n                         <div class=\"mb-3\">\n"
                },
                {
                    "date": 1666750361954,
                    "content": "Index: \n===================================================================\n--- \n+++ \n@@ -49,9 +49,9 @@\n                             <div class=\"col-12\">\n                                 <table class=\"table\">\n                                     <thead>\n                                         <tr>\n-\n+<td></td>\n                                         </tr>\n                                     </thead>\n                                 </table>\n                             </div>\n"
                },
                {
                    "date": 1666750368232,
                    "content": "Index: \n===================================================================\n--- \n+++ \n@@ -49,9 +49,10 @@\n                             <div class=\"col-12\">\n                                 <table class=\"table\">\n                                     <thead>\n                                         <tr>\n-<td></td>\n+                                            <td>Days</td>\n+                                            <td></td>\n                                         </tr>\n                                     </thead>\n                                 </table>\n                             </div>\n"
                },
                {
                    "date": 1666750392017,
                    "content": "Index: \n===================================================================\n--- \n+++ \n@@ -50,9 +50,9 @@\n                                 <table class=\"table\">\n                                     <thead>\n                                         <tr>\n                                             <td>Days</td>\n-                                            <td></td>\n+                                            <td>mileage</td>\n                                         </tr>\n                                     </thead>\n                                 </table>\n                             </div>\n"
                },
                {
                    "date": 1666750398424,
                    "content": "Index: \n===================================================================\n--- \n+++ \n@@ -51,9 +51,9 @@\n                                     <thead>\n                                         <tr>\n                                             <td>Days</td>\n                                             <td>Mileage</td>\n-                                            <td></td>\n+                                            <td>T</td>\n                                         </tr>\n                                     </thead>\n                                 </table>\n                             </div>\n"
                },
                {
                    "date": 1666750739442,
                    "content": "Index: \n===================================================================\n--- \n+++ \n@@ -64,9 +64,9 @@\n                                             <td>7200000</td>\n                                         </tr>\n                                     </thead>\n                                 </table>\n-                                <div class=\"row justify-conet\">\n+                                <div class=\"row justify-cone\">\n \n                                 </div>\n                             </div>\n                         </div>\n"
                }
            ],
            "date": 1666747747936,
            "name": "Commit-0",
            "content": "@extends('templates.main')\n@section('content')\n    <div class=\"col-md-12 grid-margin stretch-card\">\n        <div class=\"card\">\n            <div class=\"card-body\">\n                <h6 class=\"card-title\"> Master City</h6>\n                <p class=\"card-description\">Enter Your Data For City</p>\n                <div class=\"card-body\">\n                    <h6 class=\"card-title\">Basic Form</h6>\n                    <form class=\"forms-sample\" action=\"{{ route('city.store') }}\" method=\"POST\">\n                        @csrf\n                        @method('POST')\n                        <div class=\"form-group\">\n                            <div class=\"row\">\n                                <div class=\"col-md-6 col-sm-12\">\n                                    <label>Form City</label>\n                                    <select class=\"js-example w-100\" name=\"form_city_id\">\n                                        <option selected hidden>Select City</option>\n                                        @foreach ($city as $item)\n                                            <option value=\"{{ $item->id }}\">{{ $item->city }}</option>\n                                        @endforeach\n                                    </select>\n                                </div>\n                                <div class=\"col-md-6 col-sm-12\">\n                                    <label>To City</label>\n                                    <select class=\"js-example-basic w-100\" name=\"to_city_id\">\n                                        <option selected hidden>Select City</option>\n                                        @foreach ($city as $item)\n                                            <option value=\"{{ $item->id }}\">{{ $item->city }}</option>\n                                        @endforeach\n                                    </select>\n                                </div>\n\n                            </div>\n                        </div>\n                        <div class=\"form-group\">\n                            <div class=\"row\">\n                                <div class=\"col-md-6 col-sm-12\">\n                                    <label for=\"city\">Start Date</label>\n                                    <input type=\"date\" class=\"form-control @error('city') is-invalid @enderror\"\n                                        id=\"city\" autocomplete=\"off\" placeholder=\"Solo\" name=\"from\"\n                                        autocomplete=\"off\" value=\"{{ old('city') }}\">\n                                    @error('city')\n                                        <div class=\"invalid-feedback\">{{ $message }}</div>\n                                    @enderror\n                                </div>\n                                <div class=\"col-md-6 col-sm-12\">\n                                    <label for=\"to\">End Date</label>\n                                    <input type=\"date\" class=\"form-control @error('city') is-invalid @enderror\"\n                                        id=\"to\" autocomplete=\"off\" placeholder=\"Solo\" name=\"to\"\n                                        autocomplete=\"off\" value=\"{{ old('city') }}\">\n                                    @error('city')\n                                        <div class=\"invalid-feedback\">{{ $message }}</div>\n                                    @enderror\n                                </div>\n                            </div>\n                        </div>\n                        <div class=\"form-group\">\n                            <div class=\"row\">\n                                <div class=\"col-lg-12\">\n                                    <label class=\"col-form-label\">Text Area</label>\n                                    <textarea id=\"description\" class=\"form-control\" maxlength=\"100\" rows=\"8\"\n                                        placeholder=\"This textarea has a limit of 100 chars.\" name=\"desccription\"></textarea>\n                                </div>\n                            </div>\n                        </div>\n                        <div class=\"row\">\n                            <div class=\"col-md-4\"></div>\n                            <div class=\"col-md-4\">\n                                <label for=\"\" class=\"form Label\">Total Perjalaan Dinas</label>\n                                <h3>O Hari</h3>\n                            </div>\n                            <div class=\"col-md-4\"></div>\n                        </div>\n                        <div class=\"mb-3\">\n                            <button type=\"submit\" class=\"btn btn-primary mr-2\">Submit</button>\n                            <button class=\"btn btn-light\">Cancel</button>\n                        </div>\n                    </form>\n                </div>\n            </div>\n        </div>\n    </div>\n@endsection\n@push('styles')\n    <link rel=\"stylesheet\" href=\"{{ asset('assets/vendors/select2/select2.min.css') }}\">\n@endpush\n@push('scripts')\n    <script src=\"{{ asset('assets/vendors/select2/select2.min.js') }}\"></script>\n    <script src=\"{{ asset('assets/js/select2.js') }}\"></script>\n@endpush\n"
        }
    ]
}