{
    "sourceFile": "resources/views/templates/alert.blade.php",
    "activeCommit": 0,
    "commits": [
        {
            "activePatchIndex": 6,
            "patches": [
                {
                    "date": 1666496812123,
                    "content": "Index: \n===================================================================\n--- \n+++ \n"
                },
                {
                    "date": 1666496840576,
                    "content": "Index: \n===================================================================\n--- \n+++ \n@@ -1,5 +1,5 @@\n @if (session()->has('success'))\n-    <div class=\"alert alert-success\" role=\"alert\">\n+    <div class=\"alert alert-fill-primary\" role=\"alert\">\n         {{ session('success') }}\n     </div>\n @else\n"
                },
                {
                    "date": 1666496848275,
                    "content": "Index: \n===================================================================\n--- \n+++ \n@@ -2,4 +2,9 @@\n     <div class=\"alert alert-fill-primary\" role=\"alert\">\n         {{ session('success') }}\n     </div>\n @else\n+@if (session()->has('danger'))\n+    <div class=\"alert alert-fill-primary\" role=\"alert\">\n+        {{ session('success') }}\n+    </div>\n+@else\n"
                },
                {
                    "date": 1666496854005,
                    "content": "Index: \n===================================================================\n--- \n+++ \n@@ -2,9 +2,9 @@\n     <div class=\"alert alert-fill-primary\" role=\"alert\">\n         {{ session('success') }}\n     </div>\n @else\n-@if (session()->has('danger'))\n-    <div class=\"alert alert-fill-primary\" role=\"alert\">\n-        {{ session('success') }}\n-    </div>\n-@else\n+    @if (session()->has('danger'))\n+        <div class=\"alert alert-fill-danger\" role=\"alert\">\n+            {{ session('danger') }}\n+        </div>\n+    @else\n"
                },
                {
                    "date": 1666496937344,
                    "content": "Index: \n===================================================================\n--- \n+++ \n@@ -1,10 +1,10 @@\n @if (session()->has('success'))\n-    <div class=\"alert alert-fill-primary\" role=\"alert\">\n+    <div class=\"alert alert-fill-success\" role=\"alert\">\n         {{ session('success') }}\n     </div>\n @else\n     @if (session()->has('danger'))\n         <div class=\"alert alert-fill-danger\" role=\"alert\">\n             {{ session('danger') }}\n         </div>\n-    @else\n+    @e\n"
                },
                {
                    "date": 1666496944387,
                    "content": "Index: \n===================================================================\n--- \n+++ \n@@ -1,10 +1,10 @@\n @if (session()->has('success'))\n     <div class=\"alert alert-fill-success\" role=\"alert\">\n         {{ session('success') }}\n     </div>\n-@else\n-    @if (session()->has('danger'))\n-        <div class=\"alert alert-fill-danger\" role=\"alert\">\n-            {{ session('danger') }}\n-        </div>\n-    @e\n+@endif\n+@if (session()->has('danger'))\n+    <div class=\"alert alert-fill-danger\" role=\"alert\">\n+        {{ session('danger') }}\n+    </div>\n+@endif\n"
                },
                {
                    "date": 1666802489589,
                    "content": "Index: \n===================================================================\n--- \n+++ \n@@ -7,4 +7,9 @@\n     <div class=\"alert alert-fill-danger\" role=\"alert\">\n         {{ session('danger') }}\n     </div>\n @endif\n+@if (session()->has('danger'))\n+    <div class=\"alert alert-fill-danger\" role=\"alert\">\n+        {{ session('danger') }}\n+    </div>\n+@endif\n"
                }
            ],
            "date": 1666496812123,
            "name": "Commit-0",
            "content": "@if (session()->has('success'))\n    <div class=\"alert alert-success\" role=\"alert\">\n        {{ session('success') }}\n    </div>\n@else\n"
        }
    ]
}